door/__init__.py
door/core.py
door/decorators.py
door/dispatch.py
door/models/__init__.py
door/models/files/file.py
door/models/messages/message.py
door/plugins/__init__.py
door/plugins/base.py
door/plugins/commands/leave.py
door/plugins/examples/channel_joined.py
door/plugins/examples/general.py
door/run.py
door/sentry.py
door/settings.py
door/slack.py
door/utils/__init__.py
door/utils/collections.py
door/utils/interactive.py
door/utils/plugins.py
slackdoor-0.6.11.dist-info/LICENSE
slackdoor-0.6.11.dist-info/METADATA
slackdoor-0.6.11.dist-info/WHEEL
slackdoor-0.6.11.dist-info/entry_points.txt
slackdoor-0.6.11.dist-info/RECORD
